[
  {
    "address":  "4710 Sam Peck Road ",
    "city":  "Little Rock",
    "county":  "N/A",
    "zip":  "N/A",
    "po_box":  "N/A",
    "country":  "USA",
    "state":  "N/A"
  },
  {
    "address1": "8782 Cloudleap Ct ",
    "city":  "Columbia",
    "state":  "MD",
    "zip":  "21045",
    "country":  "USA",
    "po_box":  "nil",
    "mailing_address": "nil",
    "shipping_address": "nil"
  },
  {
    "address1": "4849 Connecticut Ave. NW",
    "city":  "Washington",
    "state":  "DC",
    "zip":  "20008"
  },
  {
    "address1": "625 East Monroe Ave",
    "city":  "Alexandria",
    "state":  "VA",
    "zip":  "22301",
    "country":  "United States",
    "po_box":  "nil",
    "mailing_address": "nil",
    "shipping_address": "nil"
  },
  {
    "address1": "6221 Summer Pond Drive",
    "city":  "Centreville",
    "state":  "VA",
    "postal_code":  "20121",
    "county_name":  "Fairfax",
    "lead2_lease_email":  "lakesideboz@lead2lease.com"
  },
  {
    "address": "960 Catbird Court ",
    "city":  "Memphis",
    "state":  "TN",
    "postal_code":  "38119",
    "email":  "ParkEstate.MAAC@lead2lease.com",
    "@address_type":  "property"
  }
]
